niapy/__init__.py
niapy/algorithms/__init__.py
niapy/algorithms/algorithm.py
niapy/algorithms/basic/__init__.py
niapy/algorithms/basic/abc.py
niapy/algorithms/basic/ba.py
niapy/algorithms/basic/bea.py
niapy/algorithms/basic/bfo.py
niapy/algorithms/basic/ca.py
niapy/algorithms/basic/clonalg.py
niapy/algorithms/basic/cro.py
niapy/algorithms/basic/cs.py
niapy/algorithms/basic/cso.py
niapy/algorithms/basic/de.py
niapy/algorithms/basic/es.py
niapy/algorithms/basic/fa.py
niapy/algorithms/basic/foa.py
niapy/algorithms/basic/fpa.py
niapy/algorithms/basic/fss.py
niapy/algorithms/basic/fwa.py
niapy/algorithms/basic/ga.py
niapy/algorithms/basic/gsa.py
niapy/algorithms/basic/gso.py
niapy/algorithms/basic/gwo.py
niapy/algorithms/basic/hho.py
niapy/algorithms/basic/hs.py
niapy/algorithms/basic/kh.py
niapy/algorithms/basic/loa.py
niapy/algorithms/basic/mbo.py
niapy/algorithms/basic/mfo.py
niapy/algorithms/basic/mke.py
niapy/algorithms/basic/pso.py
niapy/algorithms/basic/sca.py
niapy/algorithms/modified/__init__.py
niapy/algorithms/modified/hba.py
niapy/algorithms/modified/hde.py
niapy/algorithms/modified/hsaba.py
niapy/algorithms/modified/ilshade.py
niapy/algorithms/modified/jde.py
niapy/algorithms/modified/plba.py
niapy/algorithms/modified/saba.py
niapy/algorithms/modified/shade.py
niapy/algorithms/other/__init__.py
niapy/algorithms/other/aso.py
niapy/algorithms/other/hc.py
niapy/algorithms/other/mts.py
niapy/algorithms/other/nmm.py
niapy/algorithms/other/rs.py
niapy/algorithms/other/sa.py
niapy/callbacks.py
niapy/problems/__init__.py
niapy/problems/ackley.py
niapy/problems/alpine.py
niapy/problems/bent_cigar.py
niapy/problems/chung_reynolds.py
niapy/problems/cosine_mixture.py
niapy/problems/csendes.py
niapy/problems/discus.py
niapy/problems/dixon_price.py
niapy/problems/elliptic.py
niapy/problems/griewank.py
niapy/problems/happy_cat.py
niapy/problems/hgbat.py
niapy/problems/katsuura.py
niapy/problems/levy.py
niapy/problems/michalewicz.py
niapy/problems/perm.py
niapy-2.5.2.dist-info/LICENSE
niapy-2.5.2.dist-info/METADATA
niapy-2.5.2.dist-info/WHEEL
niapy-2.5.2.dist-info/RECORD
