Metadata-Version: 2.3
Name: niapy
Version: 2.5.2
Summary: Python micro framework for building nature-inspired algorithms.
Home-page: https://github.com/NiaOrg/NiaPy
License: MIT
Keywords: nature-inspired algorithms,evolutionary algorithms,swarm intelligence,optimization
Author: NiaOrg
Author-email: niapy.organization@gmail.com
Requires-Python: >=3.9,<3.14
Classifier: Development Status :: 5 - Production/Stable
Classifier: Intended Audience :: Developers
Classifier: Intended Audience :: Science/Research
Classifier: License :: OSI Approved :: MIT License
Classifier: Natural Language :: English
Classifier: Operating System :: OS Independent
Classifier: Programming Language :: Python :: 3
Classifier: Programming Language :: Python :: 3.9
Classifier: Programming Language :: Python :: 3.10
Classifier: Programming Language :: Python :: 3.11
Classifier: Programming Language :: Python :: 3.12
Classifier: Programming Language :: Python :: 3.13
Classifier: Topic :: Scientific/Engineering
Classifier: Topic :: Software Development
Requires-Dist: matplotlib (>=3.8.0,<4.0.0)
Requires-Dist: numpy (>=1.26.1,<2.0.0)
Requires-Dist: openpyxl (>=3.1.2,<4.0.0)
Requires-Dist: pandas (>=2.1.1,<3.0.0)
Project-URL: Documentation, https://niapy.org/en/stable/
Project-URL: Repository, https://github.com/NiaOrg/NiaPy
